nanoprobe/__init__.py
nanoprobe/cronos.py
nanoprobe-0.0.3.dist-info/DESCRIPTION.rst
nanoprobe-0.0.3.dist-info/METADATA
nanoprobe-0.0.3.dist-info/RECORD
nanoprobe-0.0.3.dist-info/WHEEL
nanoprobe-0.0.3.dist-info/metadata.json
nanoprobe-0.0.3.dist-info/top_level.txt
