Metadata-Version: 2.0
Name: nanoprobe
Version: 0.0.3
Summary: Set of tools to profile your shiny python code
Home-page: https://github.com/OrbitalAds/nanoprobe
Author: OrbitalAds
Author-email: dev@orbitalads.io
License: UNKNOWN
Keywords: profiler profiling time
Platform: UNKNOWN
Classifier: Development Status :: 3 - Alpha
Classifier: Intended Audience :: Developers
Classifier: Topic :: Software Development :: Build Tools
Classifier: License :: OSI Approved :: MIT License
Classifier: Natural Language :: English
Classifier: Programming Language :: Python :: 3
Classifier: Programming Language :: Python :: 3.4
Classifier: Programming Language :: Python :: 3.5
Classifier: Programming Language :: Python :: 3.6
Classifier: Topic :: Software Development :: Quality Assurance
